<?xml version="1.0" encoding="UTF-8"?>
<!DOCTYPE chunkList SYSTEM "ccl.dtd">
<chunkList>
 <chunk id="ch1">
  <sentence id="sent1">
   <tok>
    <orth>ja</orth>
    <lex disamb="1"><base>ja</base><ctag>ppron12:sg:nom:f:pri</ctag></lex>
    <ann chan="nam_org">0</ann>
   </tok>
   <tok>
    <orth>zrobiła</orth>
    <lex disamb="1"><base>zrobić</base><ctag>praet:sg:f:perf</ctag></lex>
    <ann chan="nam_org">0</ann>
   </tok>
   <ns/>
   <tok>
    <orth>m</orth>
    <lex disamb="1"><base>być</base><ctag>aglt:sg:pri:imperf:nwok</ctag></lex>
    <ann chan="nam_org">0</ann>
   </tok>
   <tok>
    <orth>wszystko</orth>
    <lex disamb="1"><base>wszystko</base><ctag>subst:sg:acc:n</ctag></lex>
    <ann chan="nam_org">0</ann>
   </tok>
   <tok>
    <orth>dobrze</orth>
    <lex disamb="1"><base>dobrze</base><ctag>adv:pos</ctag></lex>
    <ann chan="nam_org">0</ann>
   </tok>
   <ns/>
   <tok>
    <orth>,</orth>
    <lex disamb="1"><base>,</base><ctag>interp</ctag></lex>
    <ann chan="nam_org">0</ann>
   </tok>
   <tok>
    <orth>ale</orth>
    <lex disamb="1"><base>ale</base><ctag>conj</ctag></lex>
    <ann chan="nam_org">0</ann>
   </tok>
   <tok>
    <orth>jak</orth>
    <lex disamb="1"><base>jak</base><ctag>adv</ctag></lex>
    <ann chan="nam_org">0</ann>
   </tok>
   <tok>
    <orth>wpisywała</orth>
    <lex disamb="1"><base>wpisywać</base><ctag>praet:sg:f:imperf</ctag></lex>
    <ann chan="nam_org">0</ann>
   </tok>
   <ns/>
   <tok>
    <orth>m</orth>
    <lex disamb="1"><base>być</base><ctag>aglt:sg:pri:imperf:nwok</ctag></lex>
    <ann chan="nam_org">0</ann>
   </tok>
   <tok>
    <orth>login</orth>
    <lex disamb="1"><base>login</base><ctag>subst:sg:acc:m3</ctag></lex>
    <ann chan="nam_org">0</ann>
   </tok>
   <tok>
    <orth>i</orth>
    <lex disamb="1"><base>i</base><ctag>conj</ctag></lex>
    <ann chan="nam_org">0</ann>
   </tok>
   <tok>
    <orth>hasło</orth>
    <lex disamb="1"><base>hasło</base><ctag>subst:sg:acc:n</ctag></lex>
    <ann chan="nam_org">0</ann>
   </tok>
   <ns/>
   <tok>
    <orth>,</orth>
    <lex disamb="1"><base>,</base><ctag>interp</ctag></lex>
    <ann chan="nam_org">0</ann>
   </tok>
   <tok>
    <orth>pisało</orth>
    <lex disamb="1"><base>pisać</base><ctag>praet:sg:n:imperf</ctag></lex>
    <ann chan="nam_org">0</ann>
   </tok>
   <tok>
    <orth>że</orth>
    <lex disamb="1"><base>że</base><ctag>comp</ctag></lex>
    <ann chan="nam_org">0</ann>
   </tok>
   <tok>
    <orth>źle</orth>
    <lex disamb="1"><base>źle</base><ctag>adv:pos</ctag></lex>
    <ann chan="nam_org">0</ann>
   </tok>
   <tok>
    <orth>wpisała</orth>
    <lex disamb="1"><base>wpisać</base><ctag>praet:sg:f:perf</ctag></lex>
    <ann chan="nam_org">0</ann>
   </tok>
   <ns/>
   <tok>
    <orth>m</orth>
    <lex disamb="1"><base>być</base><ctag>aglt:sg:pri:imperf:nwok</ctag></lex>
    <ann chan="nam_org">0</ann>
   </tok>
   <ns/>
   <tok>
    <orth>,</orth>
    <lex disamb="1"><base>,</base><ctag>interp</ctag></lex>
    <ann chan="nam_org">0</ann>
   </tok>
   <tok>
    <orth>a</orth>
    <lex disamb="1"><base>a</base><ctag>conj</ctag></lex>
    <ann chan="nam_org">0</ann>
   </tok>
   <tok>
    <orth>jak</orth>
    <lex disamb="1"><base>jak</base><ctag>adv</ctag></lex>
    <ann chan="nam_org">0</ann>
   </tok>
   <tok>
    <orth>weszła</orth>
    <lex disamb="1"><base>wejść</base><ctag>praet:sg:f:perf</ctag></lex>
    <ann chan="nam_org">0</ann>
   </tok>
   <ns/>
   <tok>
    <orth>m</orth>
    <lex disamb="1"><base>być</base><ctag>aglt:sg:pri:imperf:nwok</ctag></lex>
    <ann chan="nam_org">0</ann>
   </tok>
   <tok>
    <orth>na</orth>
    <lex disamb="1"><base>na</base><ctag>prep:acc</ctag></lex>
    <ann chan="nam_org">0</ann>
   </tok>
   <tok>
    <orth>normalne</orth>
    <lex disamb="1"><base>normalny</base><ctag>adj:sg:acc:n:pos</ctag></lex>
    <ann chan="nam_org">0</ann>
   </tok>
   <tok>
    <orth>MSP</orth>
    <lex disamb="1"><base>MSP</base><ctag>subst:sg:acc:n</ctag></lex>
    <ann chan="nam_org" head="1">1</ann>
   </tok>
   <tok>
    <orth>na</orth>
    <lex disamb="1"><base>na</base><ctag>prep:loc</ctag></lex>
    <ann chan="nam_org">0</ann>
   </tok>
   <tok>
    <orth>telefonie</orth>
    <lex disamb="1"><base>telefon</base><ctag>subst:sg:loc:m3</ctag></lex>
    <ann chan="nam_org">0</ann>
   </tok>
   <tok>
    <orth>wszystko</orth>
    <lex disamb="1"><base>wszystko</base><ctag>subst:sg:nom:n</ctag></lex>
    <ann chan="nam_org">0</ann>
   </tok>
   <tok>
    <orth>było</orth>
    <lex disamb="1"><base>być</base><ctag>praet:sg:n:imperf</ctag></lex>
    <ann chan="nam_org">0</ann>
   </tok>
   <tok>
    <orth>ok</orth>
    <lex disamb="1"><base>ok</base><ctag>adv</ctag></lex>
    <ann chan="nam_org">0</ann>
   </tok>
  </sentence>
 </chunk>
</chunkList>