<?xml version="1.0" encoding="UTF-8"?>
<!DOCTYPE chunkList SYSTEM "ccl.dtd">
<chunkList>
 <chunk id="ch1">
  <sentence id="sent1">
   <tok>
    <orth>tylko</orth>
    <lex disamb="1"><base>tylko</base><ctag>qub</ctag></lex>
   </tok>
   <tok>
    <orth>to</orth>
    <lex disamb="1"><base>to</base><ctag>subst:sg:nom:n</ctag></lex>
   </tok>
   <tok>
    <orth>jak</orth>
    <lex disamb="1"><base>jak</base><ctag>adv</ctag></lex>
   </tok>
   <tok>
    <orth>wywalił</orth>
    <lex disamb="1"><base>wywalić</base><ctag>praet:sg:m1:perf</ctag></lex>
   </tok>
   <tok>
    <orth>dziewczyny</orth>
    <lex disamb="1"><base>dziewczyna</base><ctag>subst:pl:acc:f</ctag></lex>
   </tok>
   <tok>
    <orth>to</orth>
    <lex disamb="1"><base>to</base><ctag>pred</ctag></lex>
   </tok>
   <tok>
    <orth>nie</orth>
    <lex disamb="1"><base>nie</base><ctag>qub</ctag></lex>
   </tok>
   <tok>
    <orth>było</orth>
    <lex disamb="1"><base>być</base><ctag>praet:sg:n:imperf</ctag></lex>
   </tok>
   <tok>
    <orth>fajne</orth>
    <lex disamb="1"><base>fajny</base><ctag>adj:sg:nom:n:pos</ctag></lex>
   </tok>
  </sentence>
 </chunk>
</chunkList>