<?xml version="1.0" encoding="UTF-8"?>
<!DOCTYPE chunkList SYSTEM "ccl.dtd">
<chunkList>
 <chunk id="ch1">
  <sentence id="sent1">
   <tok>
    <orth>Bez</orth>
    <lex disamb="1"><base>bez</base><ctag>prep:gen:nwok</ctag></lex>
   </tok>
   <tok>
    <orth>żadnych</orth>
    <lex disamb="1"><base>żaden</base><ctag>adj:pl:gen:n:pos</ctag></lex>
   </tok>
   <tok>
    <orth>przygotowań</orth>
    <lex disamb="1"><base>przygotowanie</base><ctag>subst:pl:gen:n</ctag></lex>
   </tok>
   <ns/>
   <tok>
    <orth>,</orth>
    <lex disamb="1"><base>,</base><ctag>interp</ctag></lex>
   </tok>
   <tok>
    <orth>po</orth>
    <lex disamb="1"><base>po</base><ctag>prep:acc</ctag></lex>
   </tok>
   <tok>
    <orth>prostu</orth>
    <lex disamb="1"><base>prosty</base><ctag>adjp</ctag></lex>
   </tok>
   <tok>
    <orth>nagrane</orth>
    <lex disamb="1"><base>nagrać</base><ctag>ppas:pl:nom:n:perf:aff</ctag></lex>
   </tok>
   <tok>
    <orth>z</orth>
    <lex disamb="1"><base>z</base><ctag>prep:gen:nwok</ctag></lex>
   </tok>
   <tok>
    <orth>marszu</orth>
    <lex disamb="1"><base>marsz</base><ctag>subst:sg:gen:m3</ctag></lex>
   </tok>
   <tok>
    <orth>więc</orth>
    <lex disamb="1"><base>więc</base><ctag>conj</ctag></lex>
   </tok>
   <tok>
    <orth>i</orth>
    <lex disamb="1"><base>i</base><ctag>conj</ctag></lex>
   </tok>
   <tok>
    <orth>niedociągnięcia</orth>
    <lex disamb="1"><base>niedociągnięcie</base><ctag>subst:pl:nom:n</ctag></lex>
   </tok>
   <tok>
    <orth>są</orth>
    <lex disamb="1"><base>być</base><ctag>fin:pl:ter:imperf</ctag></lex>
   </tok>
   <tok>
    <orth>;</orth>
    <lex disamb="1"><base>;</base><ctag>interj</ctag></lex>
   </tok>
   <ns/>
   <tok>
    <orth>)</orth>
    <lex disamb="1"><base>)</base><ctag>blank</ctag></lex>
   </tok>
  </sentence>
 </chunk>
</chunkList>