<?xml version="1.0" encoding="UTF-8"?>
<!DOCTYPE chunkList SYSTEM "ccl.dtd">
<chunkList>
 <chunk id="ch1">
  <sentence id="sent1">
   <tok>
    <orth>Odpowiedzi</orth>
    <lex disamb="1"><base>odpowiedź</base><ctag>subst:pl:nom:f</ctag></lex>
   </tok>
   <tok>
    <orth>pod</orth>
    <lex disamb="1"><base>pod</base><ctag>prep:inst:nwok</ctag></lex>
   </tok>
   <tok>
    <orth>tym</orth>
    <lex disamb="1"><base>ten</base><ctag>adj:sg:inst:m3:pos</ctag></lex>
   </tok>
   <tok>
    <orth>tweetem</orth>
    <lex disamb="1"><base>tweet</base><ctag>subst:sg:inst:m3</ctag></lex>
   </tok>
   <tok>
    <orth>#</orth>
    <lex disamb="1"><base>#</base><ctag>interp</ctag></lex>
   </tok>
   <ns/>
   <tok>
    <orth>facepalm</orth>
    <lex disamb="1"><base>facepalm</base><ctag>subst:sg:nom:m3</ctag></lex>
   </tok>
   <tok>
    <orth>@www</orth>
    <lex disamb="1"><base>@www</base><ctag>subst:sg:nom:m3</ctag></lex>
   </tok>
  </sentence>
 </chunk>
</chunkList>